{
  "scenarioInformation": {
    "title": "Match Between System and the Real World",
    "faketitle": "developer mode",
    "description": "Atomic Media is a small tech startup currently working on the UI for their new photo editing software. They have laid out the basic UI in the UI Builder, but they need help choosing icons for their tool bar.\n\nOn the left side of their UI, you will see a list of tools that will be available in the final photo editing software. Match the appropriate icon with the correct tool. Remember to place the icons to the left of the correct tool name.",
    "nextUrl": "/lessons/3",
    "exitUrl": "/quiz/2"
  },
  "solutionGrids": [[
    {
      "id": "h2c",
      "bone": "MoveIcon",
      "zIndex": "100",
      "style": {
        "zIndex": "100",
        "position": "absolute",
        "left": 245,
        "top": 215.015625,
        "rect": {
          "initial": {
            "top": 730.015625,
            "left": 1635,
            "width": 75,
            "height": 30,
            "bottom": 760.015625,
            "right": 1710
          },
          "translated": {
            "top": 215.015625,
            "left": 245,
            "width": 75,
            "height": 30,
            "bottom": 245.015625,
            "right": 320
          }
        }
      }
    },
    {
      "id": "h2d",
      "bone": "SelectIcon",
      "zIndex": "100",
      "style": {
        "zIndex": "100",
        "position": "absolute",
        "left": 245,
        "top": 260.015625,
        "rect": {
          "initial": {
            "top": 820.015625,
            "left": 1635,
            "width": 75,
            "height": 30,
            "bottom": 850.015625,
            "right": 1710
          },
          "translated": {
            "top": 260.015625,
            "left": 245,
            "width": 75,
            "height": 30,
            "bottom": 290.015625,
            "right": 320
          }
        }
      }
    },
    {
      "id": "h2e",
      "bone": "ZoomIcon",
      "zIndex": "100",
      "style": {
        "zIndex": "100",
        "position": "absolute",
        "left": 245,
        "top": 305.015625,
        "rect": {
          "initial": {
            "top": 460.015625,
            "left": 1635,
            "width": 75,
            "height": 30,
            "bottom": 490.015625,
            "right": 1710
          },
          "translated": {
            "top": 305.015625,
            "left": 245,
            "width": 75,
            "height": 30,
            "bottom": 335.015625,
            "right": 320
          }
        }
      }
    },
    {
      "id": "h2g",
      "bone": "PasteIcon",
      "zIndex": "100",
      "style": {
        "zIndex": "100",
        "position": "absolute",
        "left": 245,
        "top": 395.015625,
        "rect": {
          "initial": {
            "top": 370.015625,
            "left": 1635,
            "width": 75,
            "height": 30,
            "bottom": 400.015625,
            "right": 1710
          },
          "translated": {
            "top": 395.015625,
            "left": 245,
            "width": 75,
            "height": 30,
            "bottom": 425.015625,
            "right": 320
          }
        }
      }
    },
    {
      "id": "h2f",
      "bone": "CopyIcon",
      "zIndex": "100",
      "style": {
        "zIndex": "100",
        "position": "absolute",
        "left": 245,
        "top": 350.015625,
        "rect": {
          "initial": {
            "top": 370.015625,
            "left": 1635,
            "width": 75,
            "height": 30,
            "bottom": 400.015625,
            "right": 1710
          },
          "translated": {
            "top": 350.015625,
            "left": 245,
            "width": 75,
            "height": 30,
            "bottom": 380.015625,
            "right": 320
          }
        }
      }
    },
    {
      "id": "h2i",
      "bone": "EraseIcon",
      "zIndex": "100",
      "style": {
        "zIndex": "100",
        "position": "absolute",
        "left": 245,
        "top": 485.015625,
        "rect": {
          "initial": {
            "top": 370.015625,
            "left": 1635,
            "width": 75,
            "height": 30,
            "bottom": 400.015625,
            "right": 1710
          },
          "translated": {
            "top": 485.015625,
            "left": 245,
            "width": 75,
            "height": 30,
            "bottom": 515.015625,
            "right": 320
          }
        }
      }
    },
    {
      "id": "h2h",
      "bone": "DrawIcon",
      "zIndex": "100",
      "style": {
        "zIndex": "100",
        "position": "absolute",
        "left": 245,
        "top": 440.015625,
        "rect": {
          "initial": {
            "top": 550.015625,
            "left": 1635,
            "width": 75,
            "height": 30,
            "bottom": 580.015625,
            "right": 1710
          },
          "translated": {
            "top": 440.015625,
            "left": 245,
            "width": 75,
            "height": 30,
            "bottom": 470.015625,
            "right": 320
          }
        }
      }
    },
    {
      "id": "h2j",
      "bone": "AddTextIcon",
      "zIndex": "100",
      "style": {
        "zIndex": "100",
        "position": "absolute",
        "left": 245,
        "top": 535.015625,
        "rect": {
          "initial": {
            "top": 730.015625,
            "left": 1635,
            "width": 75,
            "height": 30,
            "bottom": 760.015625,
            "right": 1710
          },
          "translated": {
            "top": 535.015625,
            "left": 245,
            "width": 75,
            "height": 30,
            "bottom": 565.015625,
            "right": 320
          }
        }
      }
    },
    {
      "id": "h2k",
      "bone": "AddShapeIcon",
      "zIndex": "100",
      "style": {
        "zIndex": "100",
        "position": "absolute",
        "left": 247.5,
        "top": 582.015625,
        "rect": {
          "initial": {
            "top": 752.015625,
            "left": 1642.5,
            "width": 75,
            "height": 30,
            "bottom": 782.015625,
            "right": 1717.5
          },
          "translated": {
            "top": 582.015625,
            "left": 247.5,
            "width": 75,
            "height": 30,
            "bottom": 612.015625,
            "right": 322.5
          }
        }
      }
    },
    {
      "id": "h2l",
      "bone": "SelectColorIcon",
      "zIndex": "100",
      "style": {
        "zIndex": "100",
        "position": "absolute",
        "left": 247.5,
        "top": 627.015625,
        "rect": {
          "initial": {
            "top": 482.015625,
            "left": 1642.5,
            "width": 75,
            "height": 30,
            "bottom": 512.015625,
            "right": 1717.5
          },
          "translated": {
            "top": 627.015625,
            "left": 247.5,
            "width": 75,
            "height": 30,
            "bottom": 657.015625,
            "right": 322.5
          }
        }
      }
    }
  ]],
  "staticWidgets": [
    {
      "id": "h2a",
      "bone": "HeuristicTwoStatic",
      "zIndex": "50",
      "style": {
        "zIndex": "50",
        "position": "absolute",
        "left": 235,
        "top": 167,
        "rect": {
          "initial": {
            "top": 177,
            "left": 225,
            "width": 1000,
            "height": 630,
            "bottom": 807,
            "right": 1225
          },
          "translated": {
            "top": 167,
            "left": 235,
            "width": 1000,
            "height": 630,
            "bottom": 797,
            "right": 1235
          }
        }
      }
    }
  ],
  "widgetData": {
    "drawer": [
      {
        "id": "h2m",
        "bone": "HomeIcon",
        "zIndex": "100",
        "style": {
          "zIndex": "100"
        }
      },
      {
        "id": "h2n",
        "bone": "GradientIcon",
        "zIndex": "100",
        "style": {
          "zIndex": "100"
        }
      },
      {
        "id": "h2r",
        "bone": "MagicWand",
        "zIndex": "100",
        "style": {
          "zIndex": "100"
        }
      },
      {
        "id": "h2q",
        "bone": "Tag",
        "zIndex": "100",
        "style": {
          "zIndex": "100"
        }
      },
      {
        "id": "h2d",
        "bone": "SelectIcon",
        "zIndex": "100",
        "style": {
          "zIndex": "100"
        }
      },
      {
        "id": "h2l",
        "bone": "SelectColorIcon",
        "zIndex": "100",
        "style": {
          "zIndex": "100"
        }
      },
      {
        "id": "h2i",
        "bone": "EraseIcon",
        "zIndex": "100",
        "style": {
          "zIndex": "100"
        }
      },
      {
        "id": "h2f",
        "bone": "CopyIcon",
        "zIndex": "100",
        "style": {
          "zIndex": "100"
        }
      },
      {
        "id": "h2g",
        "bone": "PasteIcon",
        "zIndex": "100",
        "style": {
          "zIndex": "100"
        }
      },
      {
        "id": "h2p",
        "bone": "Slantline",
        "zIndex": "100",
        "style": {
          "zIndex": "100"
        }
      },
      {
        "id": "h2e",
        "bone": "ZoomIcon",
        "zIndex": "100",
        "style": {
          "zIndex": "100"
        }
      },
      {
        "id": "h2h",
        "bone": "DrawIcon",
        "zIndex": "100",
        "style": {
          "zIndex": "100"
        }
      },
      {
        "id": "h2o",
        "bone": "ThumbtackIcon",
        "zIndex": "100",
        "style": {
          "zIndex": "100"
        }
      },
      {
        "id": "h2j",
        "bone": "AddTextIcon",
        "zIndex": "100",
        "style": {
          "zIndex": "100"
        }
      },
      {
        "id": "h2k",
        "bone": "AddShapeIcon",
        "zIndex": "100",
        "style": {
          "zIndex": "100"
        }
      },
      {
        "id": "h2c",
        "bone": "MoveIcon",
        "zIndex": "100",
        "style": {
          "zIndex": "100"
        }
      }
    ],
    "grid": []
  },
  "positioningWeight": 0.55,
  "bonesUsedWeight": 0.45
}